__main__.py
main.py
atgeneralpurposeterminalchatbot/.env
atgeneralpurposeterminalchatbot/__init__.py
atgeneralpurposeterminalchatbot/main.py
project/__init__.py
project/__main__.py
project/main.py
at_general_purpose_terminal_chatbot-2.3.dist-info/METADATA
at_general_purpose_terminal_chatbot-2.3.dist-info/WHEEL
at_general_purpose_terminal_chatbot-2.3.dist-info/entry_points.txt
at_general_purpose_terminal_chatbot-2.3.dist-info/top_level.txt
at_general_purpose_terminal_chatbot-2.3.dist-info/RECORD
