Metadata-Version: 2.4
Name: at_general_purpose_terminal_chatbot
Version: 2.3
Summary: Chatbot for general purpose tasks using LangChain and OpenAI API
Home-page: https://github.com/arthur-timoteo/general_purpose_terminal_chatbot/tree/feature-python_31012-langchain_0214/python/3.10.12/langchain/0.2.14
Author: Arthur Timoteo
Author-email: arthur.timoteo@gmail.com
License: MIT
Classifier: Programming Language :: Python :: 3.12
Classifier: License :: OSI Approved :: MIT License
Requires-Python: >=3.10
Requires-Dist: langchain_openai>=0.2.14
Requires-Dist: dotenv
Requires-Dist: rich
Dynamic: author
Dynamic: author-email
Dynamic: classifier
Dynamic: description-content-type
Dynamic: home-page
Dynamic: license
Dynamic: requires-dist
Dynamic: requires-python
Dynamic: summary
